{"id":"5a421521755f0263b7c8d2c2","name":"dfs","app_scope_id":"5a39c80d755f0241ffc8d280","description":"dfs Application for Prod","author":"Site Admin","primary":true,"created_at":1514280225,"version":3,"absolute_policies":[{"consumer_filter_id":"5a39c826755f0270c4c8d278","provider_filter_id":"5a39c80d755f0241ffc8d280","consumer_filter_name":"Default:DataCenter:dfs:dev","provider_filter_name":"Default:DataCenter:dfs:prod","l4_params":[{"port":[22,22],"proto":6},{"port":[21,21],"proto":6}],"action":"DENY","priority":10}],"default_policies":[{"consumer_filter_id":"5a41e741497d4f22824e200b","provider_filter_id":"5a5bf0af497d4f55e5727f20","consumer_filter_name":"Default:DataCenter:SDN","provider_filter_name":"sdfexdb","l4_params":[{"port":[42445,42445],"proto":6}],"action":"ALLOW","priority":100},{"consumer_filter_id":"5a39c6d0497d4f50484e1e6b","provider_filter_id":"5a5bf0af497d4f55e5727f26","consumer_filter_name":"Default:DataCenter","provider_filter_name":"scdf-es*","l4_params":[{"port":[80,80],"proto":6},{"port":[443,443],"proto":6},{"port":[5555,5555],"proto":6}],"action":"ALLOW","priority":100},{"consumer_filter_id":"5a5bf0af497d4f55e5727f2c","provider_filter_id":"5a5bf0af497d4f55e5727f26","consumer_filter_name":"10.253.42.102","provider_filter_name":"scdf-es*","l4_params":[{"port":[2314,2314],"proto":6}],"action":"ALLOW","priority":100},{"consumer_filter_id":"5a167344497d4f3576da7854","provider_filter_id":"5a5bf0af497d4f55e5727f2b","consumer_filter_name":"Default","provider_filter_name":"scdf-esmallweb","l4_params":[{"port":[0,0],"proto":6},{"port":[80,80],"proto":6},{"port":[443,443],"proto":6},{"port":[53,53],"proto":17}],"action":"ALLOW","priority":100},{"consumer_filter_id":"5a5bf0af497d4f55e5727f2b","provider_filter_id":"5a39c724497d4f4eb64e1e6b","consumer_filter_name":"scdf-esmallweb","provider_filter_name":"Default:DataCenter:nat","l4_params":[{"port":[21,21],"proto":6},{"port":[1556,1556],"proto":6},{"port":[4700,36400],"proto":6},{"port":[38769,38769],"proto":6},{"port":[40217,40217],"proto":6},{"port":[41232,41232],"proto":6},{"port":[45533,45533],"proto":6},{"port":[45734,45734],"proto":6},{"port":[49151,49151],"proto":6},{"port":[50184,50184],"proto":6},{"port":[51904,51904],"proto":6},{"port":[63454,63454],"proto":6},{"port":[123,123],"proto":17}],"action":"ALLOW","priority":100},{"consumer_filter_id":"5a39c724497d4f4eb64e1e6b","provider_filter_id":"5a5bf0af497d4f55e5727f26","consumer_filter_name":"Default:DataCenter:nat","provider_filter_name":"scdf-es*","l4_params":[{"port":[21,22],"proto":6},{"port":[80,80],"proto":6},{"port":[443,443],"proto":6},{"port":[1556,1556],"proto":6},{"port":[2314,2314],"proto":6},{"port":[5000,65535],"proto":6}],"action":"ALLOW","priority":100},{"consumer_filter_id":"5a5bf0af497d4f55e5727f28","provider_filter_id":"5a41dfc9755f025cafc8d396","consumer_filter_name":"10.253.42.*","provider_filter_name":"Default:DataCenter:ServerFarm","l4_params":[{"port":[123,123],"proto":17},{"port":[1521,1521],"proto":6},{"port":[21080,21080],"proto":6},{"port":[23090,23090],"proto":6},{"port":[32768,61000],"proto":6}],"action":"ALLOW","priority":100},{"consumer_filter_id":"5a5bf0af497d4f55e5727f2b","provider_filter_id":"5a39c6d0497d4f50484e1e6b","consumer_filter_name":"scdf-esmallweb","provider_filter_name":"Default:DataCenter","l4_params":[{"port":[30306,30306],"proto":6},{"port":[32542,32542],"proto":6},{"port":[53541,53541],"proto":6},{"port":[57169,57169],"proto":6}],"action":"ALLOW","priority":100},{"consumer_filter_id":"5a39c6d0497d4f50484e1e6b","provider_filter_id":"5a5bf0af497d4f55e5727f2a","consumer_filter_name":"Default:DataCenter","provider_filter_name":"scdf-esmallweb","l4_params":[{"port":[80,80],"proto":6},{"port":[443,443],"proto":6}],"action":"ALLOW","priority":100},{"consumer_filter_id":"5a5bf0af497d4f55e5727f26","provider_filter_id":"5a41dfc9755f025cafc8d396","consumer_filter_name":"scdf-es*","provider_filter_name":"Default:DataCenter:ServerFarm","l4_params":[{"port":[443,443],"proto":6},{"port":[1521,1521],"proto":6},{"port":[5640,5640],"proto":6}],"action":"ALLOW","priority":100},{"consumer_filter_id":"5a39c826755f0270c4c8d278","provider_filter_id":"5a5bf0af497d4f55e5727f1d","consumer_filter_name":"Default:DataCenter:dfs:dev","provider_filter_name":"csh-iux-db","l4_params":[{"port":[1523,1523],"proto":6}],"action":"ALLOW","priority":100},{"consumer_filter_id":"5a5bf0af497d4f55e5727f24","provider_filter_id":"5a167344497d4f3576da7854","consumer_filter_name":"csh-iux-biwas","provider_filter_name":"Default","l4_params":[{"port":[53,53],"proto":17},{"port":[123,123],"proto":17},{"port":[427,427],"proto":17},{"port":[20,21],"proto":6},{"port":[1556,1556],"proto":6},{"port":[21080,21080],"proto":6},{"port":[55826,55826],"proto":6},{"port":[57030,57030],"proto":6}],"action":"ALLOW","priority":100},{"consumer_filter_id":"5a5bf0af497d4f55e5727f28","provider_filter_id":"5a5bf0af497d4f55e5727f29","consumer_filter_name":"10.253.42.*","provider_filter_name":"10.253.42.101","l4_params":[{"port":[0,0],"proto":17},{"port":[2404,2404],"proto":17}],"action":"ALLOW","priority":100},{"consumer_filter_id":"5a5bf0af497d4f55e5727f29","provider_filter_id":"5a167344497d4f3576da7854","consumer_filter_name":"10.253.42.101","provider_filter_name":"Default","l4_params":[{"port":[21,21],"proto":6},{"port":[1521,1521],"proto":6},{"port":[1556,1556],"proto":6},{"port":[16741,16741],"proto":6},{"port":[27667,27667],"proto":6},{"port":[28573,28573],"proto":6},{"port":[32497,32497],"proto":6},{"port":[35394,35394],"proto":6},{"port":[43390,43390],"proto":6},{"port":[50619,50619],"proto":6},{"port":[123,123],"proto":17},{"port":[5353,5353],"proto":17}],"action":"ALLOW","priority":100},{"consumer_filter_id":"5a5bf0af497d4f55e5727f23","provider_filter_id":"5a167344497d4f3576da7854","consumer_filter_name":"cluster","provider_filter_name":"Default","l4_params":[{"port":[53,53],"proto":17},{"port":[2191,2191],"proto":17},{"port":[3030,3030],"proto":17},{"port":[5355,5355],"proto":17},{"port":[443,443],"proto":6},{"port":[1521,1521],"proto":6},{"port":[1556,1556],"proto":6},{"port":[2186,2186],"proto":6},{"port":[3140,3141],"proto":6},{"port":[4202,4202],"proto":6},{"port":[5465,5465],"proto":6},{"port":[39363,39363],"proto":6},{"port":[42639,42639],"proto":6},{"port":[55080,55080],"proto":6},{"port":[56435,56435],"proto":6},{"port":[57023,57023],"proto":6}],"action":"ALLOW","priority":100},{"consumer_filter_id":"5a5bf0af497d4f55e5727f2c","provider_filter_id":"5a41dfc9755f025cafc8d396","consumer_filter_name":"10.253.42.102","provider_filter_name":"Default:DataCenter:ServerFarm","l4_params":[{"port":[1521,1521],"proto":6},{"port":[123,123],"proto":17}],"action":"ALLOW","priority":100},{"consumer_filter_id":"5a5bf0af497d4f55e5727f2a","provider_filter_id":"5a39c6d0497d4f50484e1e6b","consumer_filter_name":"scdf-esmallweb","provider_filter_name":"Default:DataCenter","l4_params":[{"port":[31444,31444],"proto":6},{"port":[57429,57429],"proto":6}],"action":"ALLOW","priority":100},{"consumer_filter_id":"5a5bf0af497d4f55e5727f20","provider_filter_id":"5a41dfc9755f025cafc8d396","consumer_filter_name":"sdfexdb","provider_filter_name":"Default:DataCenter:ServerFarm","l4_params":[{"port":[2049,2049],"proto":6},{"port":[2314,2314],"proto":6},{"port":[21080,21080],"proto":6},{"port":[54176,54176],"proto":6},{"port":[58043,58043],"proto":6},{"port":[53,53],"proto":17},{"port":[123,123],"proto":17}],"action":"ALLOW","priority":100},{"consumer_filter_id":"5a5bf0af497d4f55e5727f25","provider_filter_id":"5a39c826755f0270c4c8d278","consumer_filter_name":"scsdf-iweb","provider_filter_name":"Default:DataCenter:dfs:dev","l4_params":[{"port":[52506,52506],"proto":6}],"action":"ALLOW","priority":100},{"consumer_filter_id":"5a167344497d4f3576da7854","provider_filter_id":"5a5bf0af497d4f55e5727f23","consumer_filter_name":"Default","provider_filter_name":"cluster","l4_params":[{"port":[3389,3389],"proto":17},{"port":[80,80],"proto":6},{"port":[443,443],"proto":6},{"port":[1433,1433],"proto":6},{"port":[1556,1556],"proto":6},{"port":[3389,3389],"proto":6},{"port":[5003,5003],"proto":6},{"port":[21003,21003],"proto":6},{"port":[21113,21113],"proto":6},{"port":[53024,53024],"proto":6},{"port":[53936,53936],"proto":6},{"port":[57038,57038],"proto":6},{"port":[65184,65184],"proto":6}],"action":"ALLOW","priority":100},{"consumer_filter_id":"5a39c826755f0270c4c8d278","provider_filter_id":"5a5bf0af497d4f55e5727f29","consumer_filter_name":"Default:DataCenter:dfs:dev","provider_filter_name":"10.253.42.101","l4_params":[{"port":[1521,1521],"proto":6},{"port":[5080,5080],"proto":6}],"action":"ALLOW","priority":100},{"consumer_filter_id":"5a5bf0af497d4f55e5727f23","provider_filter_id":"5a41e741497d4f22824e200b","consumer_filter_name":"cluster","provider_filter_name":"Default:DataCenter:SDN","l4_params":[{"port":[1521,1521],"proto":6}],"action":"ALLOW","priority":100},{"consumer_filter_id":"5a39c826755f0270c4c8d278","provider_filter_id":"5a5bf0af497d4f55e5727f25","consumer_filter_name":"Default:DataCenter:dfs:dev","provider_filter_name":"scsdf-iweb","l4_params":[{"port":[22,22],"proto":6}],"action":"ALLOW","priority":100},{"consumer_filter_id":"5a5bf0af497d4f55e5727f21","provider_filter_id":"5a41dfc9755f025cafc8d396","consumer_filter_name":"csh-iedi_scsdf-iedi-inf","provider_filter_name":"Default:DataCenter:ServerFarm","l4_params":[{"port":[53,53],"proto":17},{"port":[123,123],"proto":17},{"port":[137,138],"proto":17},{"port":[1433,1433],"proto":6},{"port":[2186,2187],"proto":6},{"port":[2191,2191],"proto":6},{"port":[5465,5465],"proto":6},{"port":[21080,21080],"proto":6},{"port":[34414,34414],"proto":6},{"port":[39123,39123],"proto":6},{"port":[40623,40623],"proto":6},{"port":[42155,42155],"proto":6},{"port":[45674,45674],"proto":6}],"action":"ALLOW","priority":100},{"consumer_filter_id":"5a5bf0af497d4f55e5727f28","provider_filter_id":"5a5bf0af497d4f55e5727f23","consumer_filter_name":"10.253.42.*","provider_filter_name":"cluster","l4_params":[{"port":[1433,1433],"proto":6}],"action":"ALLOW","priority":100},{"consumer_filter_id":"5a41dfc9755f025cafc8d396","provider_filter_id":"5a5bf0af497d4f55e5727f22","consumer_filter_name":"Default:DataCenter:ServerFarm","provider_filter_name":"scsdf-iwas","l4_params":[{"port":[1556,1556],"proto":6},{"port":[7012,7012],"proto":6},{"port":[9736,9736],"proto":6},{"port":[30041,30041],"proto":6},{"port":[31003,31003],"proto":6},{"port":[34592,34592],"proto":6},{"port":[36536,36536],"proto":6},{"port":[40252,40252],"proto":6},{"port":[41310,41310],"proto":6},{"port":[46516,46516],"proto":6}],"action":"ALLOW","priority":100},{"consumer_filter_id":"5a167344497d4f3576da7854","provider_filter_id":"5a5bf0af497d4f55e5727f26","consumer_filter_name":"Default","provider_filter_name":"scdf-es*","l4_params":[{"port":[53,53],"proto":17},{"port":[80,80],"proto":6},{"port":[443,443],"proto":6},{"port":[10121,10121],"proto":6},{"port":[10168,10168],"proto":6},{"port":[10190,10190],"proto":6},{"port":[10198,10198],"proto":6},{"port":[10262,10262],"proto":6},{"port":[10578,10578],"proto":6},{"port":[10613,10613],"proto":6},{"port":[10630,13330],"proto":6},{"port":[13405,13405],"proto":6},{"port":[13702,13702],"proto":6},{"port":[56719,56719],"proto":6},{"port":[58221,58221],"proto":6}],"action":"ALLOW","priority":100},{"consumer_filter_id":"5a41dfc9755f025cafc8d396","provider_filter_id":"5a5bf0af497d4f55e5727f20","consumer_filter_name":"Default:DataCenter:ServerFarm","provider_filter_name":"sdfexdb","l4_params":[{"port":[1556,1556],"proto":6},{"port":[30041,30041],"proto":6},{"port":[31003,31003],"proto":6}],"action":"ALLOW","priority":100},{"consumer_filter_id":"5a5bf0af497d4f55e5727f22","provider_filter_id":"5a167344497d4f3576da7854","consumer_filter_name":"scsdf-iwas","provider_filter_name":"Default","l4_params":[{"port":[20,22],"proto":6},{"port":[80,80],"proto":6},{"port":[449,449],"proto":6},{"port":[1122,1122],"proto":6},{"port":[1180,1180],"proto":6},{"port":[1230,1230],"proto":6},{"port":[1239,1239],"proto":6},{"port":[1242,1242],"proto":6},{"port":[1249,1251],"proto":6},{"port":[1253,1253],"proto":6},{"port":[1257,1257],"proto":6},{"port":[1260,2383],"proto":6},{"port":[2393,2393],"proto":6},{"port":[2405,2405],"proto":6},{"port":[2411,2411],"proto":6},{"port":[2435,2435],"proto":6},{"port":[2453,2453],"proto":6},{"port":[2478,2478],"proto":6},{"port":[2491,2491],"proto":6},{"port":[2501,2501],"proto":6},{"port":[2505,2505],"proto":6},{"port":[2551,2551],"proto":6},{"port":[2607,2607],"proto":6},{"port":[2677,2677],"proto":6},{"port":[2738,2738],"proto":6},{"port":[2779,2779],"proto":6},{"port":[2961,2961],"proto":6},{"port":[3158,3158],"proto":6},{"port":[3550,3550],"proto":6},{"port":[3560,3560],"proto":6},{"port":[3658,3658],"proto":6},{"port":[3890,3890],"proto":6},{"port":[3896,3896],"proto":6},{"port":[4227,4227],"proto":6},{"port":[4395,4395],"proto":6},{"port":[7340,7340],"proto":6},{"port":[9900,9900],"proto":6},{"port":[10255,10255],"proto":6},{"port":[15030,15030],"proto":6},{"port":[18471,18471],"proto":6},{"port":[18476,18476],"proto":6},{"port":[21080,21080],"proto":6},{"port":[21511,21511],"proto":6},{"port":[23159,23159],"proto":6},{"port":[29077,29077],"proto":6},{"port":[36423,36423],"proto":6},{"port":[40387,40387],"proto":6},{"port":[42380,42380],"proto":6},{"port":[44956,44956],"proto":6},{"port":[49161,49161],"proto":6},{"port":[49172,49172],"proto":6},{"port":[49176,49177],"proto":6},{"port":[49187,49187],"proto":6},{"port":[49193,49193],"proto":6},{"port":[49195,49195],"proto":6},{"port":[49203,49203],"proto":6},{"port":[49207,49207],"proto":6},{"port":[49220,49220],"proto":6},{"port":[49229,49229],"proto":6},{"port":[49245,61978],"proto":6},{"port":[61980,65535],"proto":6},{"port":[53,53],"proto":17},{"port":[123,123],"proto":17},{"port":[33437,33437],"proto":17},{"port":[33446,33446],"proto":17},{"port":[33453,33453],"proto":17},{"port":[33458,33458],"proto":17},{"port":[33460,33461],"proto":17},{"port":[33463,33463],"proto":17}],"action":"ALLOW","priority":100},{"consumer_filter_id":"5a5bf0af497d4f55e5727f23","provider_filter_id":"5a5bf0af497d4f55e5727f29","consumer_filter_name":"cluster","provider_filter_name":"10.253.42.101","l4_params":[{"port":[1521,1521],"proto":6}],"action":"ALLOW","priority":100},{"consumer_filter_id":"5a5bf0af497d4f55e5727f26","provider_filter_id":"5a39c724497d4f4eb64e1e6b","consumer_filter_name":"scdf-es*","provider_filter_name":"Default:DataCenter:nat","l4_params":[{"port":[21,21],"proto":6},{"port":[1521,1521],"proto":6},{"port":[1556,1556],"proto":6},{"port":[4700,36400],"proto":6},{"port":[36443,36443],"proto":6},{"port":[36647,36647],"proto":6},{"port":[36844,36844],"proto":6},{"port":[36859,36859],"proto":6},{"port":[36917,36917],"proto":6},{"port":[36990,36990],"proto":6},{"port":[37110,37110],"proto":6},{"port":[37277,37277],"proto":6},{"port":[37302,37302],"proto":6},{"port":[37620,37620],"proto":6},{"port":[37699,37699],"proto":6},{"port":[37790,37790],"proto":6},{"port":[38218,38218],"proto":6},{"port":[38233,38233],"proto":6},{"port":[38449,38449],"proto":6},{"port":[38820,60000],"proto":6},{"port":[60445,60445],"proto":6},{"port":[60922,60922],"proto":6},{"port":[62744,62744],"proto":6},{"port":[62802,62802],"proto":6},{"port":[64943,64943],"proto":6},{"port":[123,123],"proto":17}],"action":"ALLOW","priority":100},{"consumer_filter_id":"5a167344497d4f3576da7854","provider_filter_id":"5a5bf0af497d4f55e5727f25","consumer_filter_name":"Default","provider_filter_name":"scsdf-iweb","l4_params":[{"port":[22,22],"proto":6},{"port":[443,443],"proto":6},{"port":[1556,1556],"proto":6},{"port":[5002,5003],"proto":6},{"port":[21003,21003],"proto":6},{"port":[21113,21113],"proto":6},{"port":[39287,39287],"proto":6},{"port":[39930,39930],"proto":6},{"port":[43999,43999],"proto":17}],"action":"ALLOW","priority":100},{"consumer_filter_id":"5a5bf0af497d4f55e5727f26","provider_filter_id":"5a39c6d0497d4f50484e1e6b","consumer_filter_name":"scdf-es*","provider_filter_name":"Default:DataCenter","l4_params":[{"port":[53,53],"proto":17},{"port":[2049,2049],"proto":6},{"port":[16204,16204],"proto":6},{"port":[16267,16267],"proto":6},{"port":[33704,33704],"proto":6},{"port":[37913,37913],"proto":6},{"port":[52647,52647],"proto":6},{"port":[53593,53593],"proto":6},{"port":[53630,53630],"proto":6}],"action":"ALLOW","priority":100},{"consumer_filter_id":"5a5bf0af497d4f55e5727f28","provider_filter_id":"5a167344497d4f3576da7854","consumer_filter_name":"10.253.42.*","provider_filter_name":"Default","l4_params":[{"port":[21,21],"proto":6},{"port":[80,80],"proto":6},{"port":[443,443],"proto":6},{"port":[1556,1556],"proto":6},{"port":[3080,3080],"proto":6},{"port":[6239,6239],"proto":6},{"port":[8523,8523],"proto":6},{"port":[9006,9006],"proto":6},{"port":[13724,13724],"proto":6},{"port":[14653,14653],"proto":6},{"port":[18376,18376],"proto":6},{"port":[21080,21080],"proto":6},{"port":[25082,25082],"proto":6},{"port":[27003,27003],"proto":6},{"port":[32975,32975],"proto":6},{"port":[32994,32994],"proto":6},{"port":[33335,33335],"proto":6},{"port":[35086,35086],"proto":6},{"port":[35439,35439],"proto":6},{"port":[36404,36404],"proto":6},{"port":[36751,36751],"proto":6},{"port":[37122,37122],"proto":6},{"port":[39200,47600],"proto":6},{"port":[48878,48878],"proto":6},{"port":[49245,61978],"proto":6},{"port":[62523,62523],"proto":6},{"port":[62656,62656],"proto":6},{"port":[62904,62904],"proto":6},{"port":[64000,64000],"proto":6},{"port":[64439,64439],"proto":6},{"port":[123,123],"proto":17},{"port":[33439,33439],"proto":17},{"port":[33444,33446],"proto":17},{"port":[33450,33450],"proto":17},{"port":[33452,33452],"proto":17},{"port":[33455,33455],"proto":17},{"port":[33462,33462],"proto":17},{"port":[33464,33464],"proto":17},{"port":[33469,33469],"proto":17},{"port":[33471,33471],"proto":17},{"port":[33484,33484],"proto":17},{"port":[33495,33495],"proto":17},{"port":[33497,33497],"proto":17},{"port":[33502,33503],"proto":17},{"port":[33506,33507],"proto":17},{"port":[33510,33510],"proto":17},{"port":[33516,33516],"proto":17},{"port":[33518,33519],"proto":17}],"action":"ALLOW","priority":100},{"consumer_filter_id":"5a5bf0af497d4f55e5727f2c","provider_filter_id":"5a5bf0af497d4f55e5727f29","consumer_filter_name":"10.253.42.102","provider_filter_name":"10.253.42.101","l4_params":[{"port":[1830,1830],"proto":6},{"port":[6200,6200],"proto":6},{"port":[23521,23521],"proto":6},{"port":[26421,26421],"proto":6},{"port":[30418,30418],"proto":6},{"port":[36874,36874],"proto":6},{"port":[40715,40715],"proto":6},{"port":[42351,42351],"proto":6},{"port":[47632,47632],"proto":6}],"action":"ALLOW","priority":100},{"consumer_filter_id":"5a43193c497d4f44784e1ee6","provider_filter_id":"5a5bf0af497d4f55e5727f26","consumer_filter_name":"Default:Public","provider_filter_name":"scdf-es*","l4_params":[{"port":[80,80],"proto":6},{"port":[1556,1556],"proto":6}],"action":"ALLOW","priority":100},{"consumer_filter_id":"5a43193c497d4f44784e1ee6","provider_filter_id":"5a5bf0af497d4f55e5727f2a","consumer_filter_name":"Default:Public","provider_filter_name":"scdf-esmallweb","l4_params":[{"port":[1556,1556],"proto":6}],"action":"ALLOW","priority":100},{"consumer_filter_id":"5a5bf0af497d4f55e5727f2b","provider_filter_id":"5a5bf0af497d4f55e5727f26","consumer_filter_name":"scdf-esmallweb","provider_filter_name":"scdf-es*","l4_params":[{"port":[2314,2314],"proto":6}],"action":"ALLOW","priority":100},{"consumer_filter_id":"5a5bf0af497d4f55e5727f1d","provider_filter_id":"5a41dfc9755f025cafc8d396","consumer_filter_name":"csh-iux-db","provider_filter_name":"Default:DataCenter:ServerFarm","l4_params":[{"port":[427,427],"proto":17}],"action":"ALLOW","priority":100},{"consumer_filter_id":"5a5bf0af497d4f55e5727f28","provider_filter_id":"5a5bf0af497d4f55e5727f26","consumer_filter_name":"10.253.42.*","provider_filter_name":"scdf-es*","l4_params":[{"port":[20,21],"proto":6},{"port":[2314,2314],"proto":6},{"port":[5000,65535],"proto":6}],"action":"ALLOW","priority":100},{"consumer_filter_id":"5a39c724497d4f4eb64e1e6b","provider_filter_id":"5a5bf0af497d4f55e5727f2a","consumer_filter_name":"Default:DataCenter:nat","provider_filter_name":"scdf-esmallweb","l4_params":[{"port":[22,22],"proto":6},{"port":[80,80],"proto":6},{"port":[443,443],"proto":6},{"port":[1556,1556],"proto":6},{"port":[5002,5003],"proto":6},{"port":[9900,9900],"proto":6},{"port":[21003,21003],"proto":6},{"port":[21113,21113],"proto":6},{"port":[30041,30041],"proto":6},{"port":[31003,31003],"proto":6}],"action":"ALLOW","priority":100},{"consumer_filter_id":"5a5bf0af497d4f55e5727f2a","provider_filter_id":"5a41dfc9755f025cafc8d396","consumer_filter_name":"scdf-esmallweb","provider_filter_name":"Default:DataCenter:ServerFarm","l4_params":[{"port":[443,443],"proto":6},{"port":[5640,5640],"proto":6}],"action":"ALLOW","priority":100},{"consumer_filter_id":"5a167344497d4f3576da7854","provider_filter_id":"5a5bf0af497d4f55e5727f22","consumer_filter_name":"Default","provider_filter_name":"scsdf-iwas","l4_params":[{"port":[123,123],"proto":17},{"port":[137,137],"proto":17},{"port":[20,22],"proto":6},{"port":[1556,1556],"proto":6},{"port":[5000,6560],"proto":6},{"port":[6572,65535],"proto":6}],"action":"ALLOW","priority":100},{"consumer_filter_id":"5a41dfc9755f025cafc8d396","provider_filter_id":"5a5bf0af497d4f55e5727f29","consumer_filter_name":"Default:DataCenter:ServerFarm","provider_filter_name":"10.253.42.101","l4_params":[{"port":[1522,1522],"proto":6},{"port":[1556,1556],"proto":6},{"port":[1830,1830],"proto":6},{"port":[31003,31003],"proto":6}],"action":"ALLOW","priority":100},{"consumer_filter_id":"5a5bf0af497d4f55e5727f22","provider_filter_id":"5a43193c497d4f44784e1ee6","consumer_filter_name":"scsdf-iwas","provider_filter_name":"Default:Public","l4_params":[{"port":[9900,9900],"proto":6}],"action":"ALLOW","priority":100},{"consumer_filter_id":"5a5bf0af497d4f55e5727f29","provider_filter_id":"5a5bf0af497d4f55e5727f1d","consumer_filter_name":"10.253.42.101","provider_filter_name":"csh-iux-db","l4_params":[{"port":[1523,1523],"proto":6}],"action":"ALLOW","priority":100},{"consumer_filter_id":"5a5bf0af497d4f55e5727f28","provider_filter_id":"5a5bf0af497d4f55e5727f2b","consumer_filter_name":"10.253.42.*","provider_filter_name":"scdf-esmallweb","l4_params":[{"port":[9900,9903],"proto":6}],"action":"ALLOW","priority":100},{"consumer_filter_id":"5a5bf0af497d4f55e5727f22","provider_filter_id":"5a41e741497d4f22824e200b","consumer_filter_name":"scsdf-iwas","provider_filter_name":"Default:DataCenter:SDN","l4_params":[{"port":[1521,1521],"proto":6}],"action":"ALLOW","priority":100},{"consumer_filter_id":"5a41dfc9755f025cafc8d396","provider_filter_id":"5a5bf0af497d4f55e5727f21","consumer_filter_name":"Default:DataCenter:ServerFarm","provider_filter_name":"csh-iedi_scsdf-iedi-inf","l4_params":[{"port":[1556,1556],"proto":6},{"port":[30041,30041],"proto":6},{"port":[5355,5355],"proto":17}],"action":"ALLOW","priority":100},{"consumer_filter_id":"5a5bf0af497d4f55e5727f26","provider_filter_id":"5a5bf0af497d4f55e5727f26","consumer_filter_name":"scdf-es*","provider_filter_name":"scdf-es*","l4_params":[{"port":[80,80],"proto":6},{"port":[5556,5559],"proto":6}],"action":"ALLOW","priority":100},{"consumer_filter_id":"5a5bf0af497d4f55e5727f25","provider_filter_id":"5a41dfc9755f025cafc8d396","consumer_filter_name":"scsdf-iweb","provider_filter_name":"Default:DataCenter:ServerFarm","l4_params":[{"port":[2314,2314],"proto":6},{"port":[21080,21080],"proto":6},{"port":[33879,33879],"proto":6},{"port":[123,123],"proto":17}],"action":"ALLOW","priority":100},{"consumer_filter_id":"5a167344497d4f3576da7854","provider_filter_id":"5a5bf0af497d4f55e5727f24","consumer_filter_name":"Default","provider_filter_name":"csh-iux-biwas","l4_params":[{"port":[1556,1556],"proto":6},{"port":[8080,8080],"proto":6},{"port":[21003,21003],"proto":6},{"port":[21113,21113],"proto":6}],"action":"ALLOW","priority":100},{"consumer_filter_id":"5a5bf0af497d4f55e5727f29","provider_filter_id":"5a39c826755f0270c4c8d278","consumer_filter_name":"10.253.42.101","provider_filter_name":"Default:DataCenter:dfs:dev","l4_params":[{"port":[7001,7001],"proto":6}],"action":"ALLOW","priority":100},{"consumer_filter_id":"5a5bf0af497d4f55e5727f28","provider_filter_id":"5a41e741497d4f22824e200b","consumer_filter_name":"10.253.42.*","provider_filter_name":"Default:DataCenter:SDN","l4_params":[{"port":[1521,1521],"proto":6}],"action":"ALLOW","priority":100},{"consumer_filter_id":"5a5bf0af497d4f55e5727f2c","provider_filter_id":"5a39c826755f0270c4c8d278","consumer_filter_name":"10.253.42.102","provider_filter_name":"Default:DataCenter:dfs:dev","l4_params":[{"port":[7001,7001],"proto":6}],"action":"ALLOW","priority":100},{"consumer_filter_id":"5a5bf0af497d4f55e5727f24","provider_filter_id":"5a43193c497d4f44784e1ee6","consumer_filter_name":"csh-iux-biwas","provider_filter_name":"Default:Public","l4_params":[{"port":[25,25],"proto":6}],"action":"ALLOW","priority":100},{"consumer_filter_id":"5a5bf0af497d4f55e5727f25","provider_filter_id":"5a5bf0af497d4f55e5727f22","consumer_filter_name":"scsdf-iweb","provider_filter_name":"scsdf-iwas","l4_params":[{"port":[22,22],"proto":6}],"action":"ALLOW","priority":100},{"consumer_filter_id":"5a167344497d4f3576da7854","provider_filter_id":"5a5bf0af497d4f55e5727f29","consumer_filter_name":"Default","provider_filter_name":"10.253.42.101","l4_params":[{"port":[22,22],"proto":6},{"port":[1521,1522],"proto":6},{"port":[1556,1556],"proto":6},{"port":[21003,21003],"proto":6},{"port":[21113,21113],"proto":6},{"port":[57819,57819],"proto":6}],"action":"ALLOW","priority":100},{"consumer_filter_id":"5a5bf0af497d4f55e5727f22","provider_filter_id":"5a41dfc9755f025cafc8d396","consumer_filter_name":"scsdf-iwas","provider_filter_name":"Default:DataCenter:ServerFarm","l4_params":[{"port":[22,22],"proto":6},{"port":[1433,1433],"proto":6},{"port":[1521,1521],"proto":6},{"port":[2049,2049],"proto":6},{"port":[2314,2314],"proto":6},{"port":[7040,7040],"proto":6},{"port":[7200,7200],"proto":6},{"port":[21080,21080],"proto":6},{"port":[44930,44930],"proto":6},{"port":[55186,55186],"proto":6},{"port":[59737,59737],"proto":6},{"port":[123,123],"proto":17}],"action":"ALLOW","priority":100},{"consumer_filter_id":"5a5bf0af497d4f55e5727f2c","provider_filter_id":"5a41e741497d4f22824e200b","consumer_filter_name":"10.253.42.102","provider_filter_name":"Default:DataCenter:SDN","l4_params":[{"port":[1521,1521],"proto":6}],"action":"ALLOW","priority":100},{"consumer_filter_id":"5a5bf0af497d4f55e5727f29","provider_filter_id":"5a5bf0af497d4f55e5727f2c","consumer_filter_name":"10.253.42.101","provider_filter_name":"10.253.42.102","l4_params":[{"port":[1830,1830],"proto":6},{"port":[19301,19301],"proto":6},{"port":[26565,26565],"proto":6},{"port":[27354,27354],"proto":6},{"port":[32447,32447],"proto":6},{"port":[41001,41001],"proto":6},{"port":[45672,45672],"proto":6},{"port":[47632,47632],"proto":6},{"port":[52070,52070],"proto":6},{"port":[56340,56340],"proto":6}],"action":"ALLOW","priority":100},{"consumer_filter_id":"5a41dfc9755f025cafc8d396","provider_filter_id":"5a5bf0af497d4f55e5727f1d","consumer_filter_name":"Default:DataCenter:ServerFarm","provider_filter_name":"csh-iux-db","l4_params":[{"port":[1523,1523],"proto":6}],"action":"ALLOW","priority":100},{"consumer_filter_id":"5a5bf0af497d4f55e5727f27","provider_filter_id":"5a41dfc9755f025cafc8d396","consumer_filter_name":"dr-sdfmallexdb_dr-sdfexdb","provider_filter_name":"Default:DataCenter:ServerFarm","l4_params":[{"port":[53,53],"proto":17},{"port":[2049,2049],"proto":6}],"action":"ALLOW","priority":100},{"consumer_filter_id":"5a5bf0af497d4f55e5727f2b","provider_filter_id":"5a167344497d4f3576da7854","consumer_filter_name":"scdf-esmallweb","provider_filter_name":"Default","l4_params":[{"port":[123,123],"proto":17}],"action":"ALLOW","priority":100},{"consumer_filter_id":"5a5bf0af497d4f55e5727f26","provider_filter_id":"5a43193c497d4f44784e1ee6","consumer_filter_name":"scdf-es*","provider_filter_name":"Default:Public","l4_params":[{"port":[53,53],"proto":17},{"port":[25,25],"proto":6}],"action":"ALLOW","priority":100},{"consumer_filter_id":"5a39c6d0497d4f50484e1e6b","provider_filter_id":"5a5bf0af497d4f55e5727f2b","consumer_filter_name":"Default:DataCenter","provider_filter_name":"scdf-esmallweb","l4_params":[{"port":[80,80],"proto":6},{"port":[443,443],"proto":6}],"action":"ALLOW","priority":100},{"consumer_filter_id":"5a167344497d4f3576da7854","provider_filter_id":"5a5bf0af497d4f55e5727f21","consumer_filter_name":"Default","provider_filter_name":"csh-iedi_scsdf-iedi-inf","l4_params":[{"port":[1556,1556],"proto":6},{"port":[3389,3389],"proto":6},{"port":[5002,5003],"proto":6},{"port":[21003,21003],"proto":6},{"port":[21113,21113],"proto":6},{"port":[53877,53877],"proto":6},{"port":[62564,62564],"proto":6},{"port":[62751,62751],"proto":6},{"port":[3389,3389],"proto":17}],"action":"ALLOW","priority":100},{"consumer_filter_id":"5a5bf0af497d4f55e5727f20","provider_filter_id":"5a41e741497d4f22824e200b","consumer_filter_name":"sdfexdb","provider_filter_name":"Default:DataCenter:SDN","l4_params":[{"port":[1521,1521],"proto":6}],"action":"ALLOW","priority":100},{"consumer_filter_id":"5a41dfc9755f025cafc8d396","provider_filter_id":"5a5bf0af497d4f55e5727f28","consumer_filter_name":"Default:DataCenter:ServerFarm","provider_filter_name":"10.253.42.*","l4_params":[{"port":[1556,1556],"proto":6},{"port":[21303,21303],"proto":6},{"port":[31003,31003],"proto":6}],"action":"ALLOW","priority":100},{"consumer_filter_id":"5a41dfc9755f025cafc8d396","provider_filter_id":"5a5bf0af497d4f55e5727f2c","consumer_filter_name":"Default:DataCenter:ServerFarm","provider_filter_name":"10.253.42.102","l4_params":[{"port":[1556,1556],"proto":6},{"port":[1830,1830],"proto":6},{"port":[31003,31003],"proto":6}],"action":"ALLOW","priority":100},{"consumer_filter_id":"5a5bf0af497d4f55e5727f2a","provider_filter_id":"5a167344497d4f3576da7854","consumer_filter_name":"scdf-esmallweb","provider_filter_name":"Default","l4_params":[{"port":[123,123],"proto":17},{"port":[5260,5260],"proto":17},{"port":[63479,63479],"proto":17}],"action":"ALLOW","priority":100},{"consumer_filter_id":"5a5bf0af497d4f55e5727f25","provider_filter_id":"5a167344497d4f3576da7854","consumer_filter_name":"scsdf-iweb","provider_filter_name":"Default","l4_params":[{"port":[21,21],"proto":6},{"port":[1556,1556],"proto":6},{"port":[21080,21080],"proto":6},{"port":[33872,33872],"proto":6},{"port":[34260,34260],"proto":6},{"port":[34899,34899],"proto":6},{"port":[36370,36370],"proto":6},{"port":[40795,40795],"proto":6},{"port":[41002,41002],"proto":6},{"port":[41876,41876],"proto":6},{"port":[43655,43655],"proto":6},{"port":[43683,43683],"proto":6},{"port":[44406,44406],"proto":6},{"port":[45303,45303],"proto":6},{"port":[45812,45812],"proto":6},{"port":[45984,45984],"proto":6},{"port":[47809,47809],"proto":6},{"port":[47992,47992],"proto":6},{"port":[48259,48259],"proto":6},{"port":[49245,61978],"proto":6},{"port":[65478,65478],"proto":6},{"port":[53,53],"proto":17},{"port":[123,123],"proto":17}],"action":"ALLOW","priority":100},{"consumer_filter_id":"5a5bf0af497d4f55e5727f22","provider_filter_id":"5a5bf0af497d4f55e5727f25","consumer_filter_name":"scsdf-iwas","provider_filter_name":"scsdf-iweb","l4_params":[{"port":[22,22],"proto":6},{"port":[9900,9900],"proto":6}],"action":"ALLOW","priority":100},{"consumer_filter_id":"5a41dfc9755f025cafc8d396","provider_filter_id":"5a5bf0af497d4f55e5727f27","consumer_filter_name":"Default:DataCenter:ServerFarm","provider_filter_name":"dr-sdfmallexdb_dr-sdfexdb","l4_params":[{"port":[21003,21003],"proto":6},{"port":[30041,30041],"proto":6},{"port":[31003,31003],"proto":6}],"action":"ALLOW","priority":100},{"consumer_filter_id":"5a5bf0af497d4f55e5727f29","provider_filter_id":"5a41e741497d4f22824e200b","consumer_filter_name":"10.253.42.101","provider_filter_name":"Default:DataCenter:SDN","l4_params":[{"port":[1521,1521],"proto":6}],"action":"ALLOW","priority":100},{"consumer_filter_id":"5a5bf0af497d4f55e5727f28","provider_filter_id":"5a39c6d0497d4f50484e1e6b","consumer_filter_name":"10.253.42.*","provider_filter_name":"Default:DataCenter","l4_params":[{"port":[53,53],"proto":17},{"port":[80,80],"proto":6},{"port":[3690,3690],"proto":6},{"port":[5555,5555],"proto":6}],"action":"ALLOW","priority":100},{"consumer_filter_id":"5a5bf0af497d4f55e5727f23","provider_filter_id":"5a5bf0af497d4f55e5727f28","consumer_filter_name":"cluster","provider_filter_name":"10.253.42.*","l4_params":[{"port":[45041,45041],"proto":6},{"port":[48067,48067],"proto":6}],"action":"ALLOW","priority":100},{"consumer_filter_id":"5a167344497d4f3576da7854","provider_filter_id":"5a5bf0af497d4f55e5727f28","consumer_filter_name":"Default","provider_filter_name":"10.253.42.*","l4_params":[{"port":[22,22],"proto":6},{"port":[1556,1556],"proto":6},{"port":[5002,5003],"proto":6},{"port":[7736,7736],"proto":6},{"port":[21003,21003],"proto":6},{"port":[21113,21113],"proto":6},{"port":[53153,53153],"proto":6},{"port":[59327,59327],"proto":6}],"action":"ALLOW","priority":100},{"consumer_filter_id":"5a5bf0af497d4f55e5727f29","provider_filter_id":"5a41dfc9755f025cafc8d396","consumer_filter_name":"10.253.42.101","provider_filter_name":"Default:DataCenter:ServerFarm","l4_params":[{"port":[1521,1522],"proto":6},{"port":[123,123],"proto":17}],"action":"ALLOW","priority":100},{"consumer_filter_id":"5a39c826755f0270c4c8d278","provider_filter_id":"5a5bf0af497d4f55e5727f26","consumer_filter_name":"Default:DataCenter:dfs:dev","provider_filter_name":"scdf-es*","l4_params":[{"port":[21,21],"proto":6},{"port":[5258,5258],"proto":6},{"port":[5555,5555],"proto":6},{"port":[6572,65535],"proto":6}],"action":"ALLOW","priority":100},{"consumer_filter_id":"5a5bf0af497d4f55e5727f28","provider_filter_id":"5a5bf0af497d4f55e5727f2a","consumer_filter_name":"10.253.42.*","provider_filter_name":"scdf-esmallweb","l4_params":[{"port":[9900,9900],"proto":6}],"action":"ALLOW","priority":100},{"consumer_filter_id":"5a5bf0af497d4f55e5727f29","provider_filter_id":"5a5bf0af497d4f55e5727f26","consumer_filter_name":"10.253.42.101","provider_filter_name":"scdf-es*","l4_params":[{"port":[2314,2314],"proto":6}],"action":"ALLOW","priority":100},{"consumer_filter_id":"5a167344497d4f3576da7854","provider_filter_id":"5a5bf0af497d4f55e5727f20","consumer_filter_name":"Default","provider_filter_name":"sdfexdb","l4_params":[{"port":[22,22],"proto":6},{"port":[1211,1211],"proto":6},{"port":[1521,1521],"proto":6},{"port":[1556,1556],"proto":6},{"port":[19600,19600],"proto":6},{"port":[21003,21003],"proto":6},{"port":[21113,21113],"proto":6},{"port":[41023,41023],"proto":6},{"port":[51740,51740],"proto":6},{"port":[51810,51810],"proto":6},{"port":[51944,51944],"proto":6},{"port":[52024,52024],"proto":6},{"port":[52206,52206],"proto":6}],"action":"ALLOW","priority":100},{"consumer_filter_id":"5a5bf0af497d4f55e5727f27","provider_filter_id":"5a167344497d4f3576da7854","consumer_filter_name":"dr-sdfmallexdb_dr-sdfexdb","provider_filter_name":"Default","l4_params":[{"port":[53,53],"proto":17},{"port":[123,123],"proto":17},{"port":[5353,5353],"proto":17}],"action":"ALLOW","priority":100},{"consumer_filter_id":"5a5bf0af497d4f55e5727f26","provider_filter_id":"5a39c826755f0270c4c8d278","consumer_filter_name":"scdf-es*","provider_filter_name":"Default:DataCenter:dfs:dev","l4_params":[{"port":[35378,35378],"proto":6},{"port":[39622,39622],"proto":6},{"port":[41096,41096],"proto":6},{"port":[44709,44709],"proto":6},{"port":[51839,51839],"proto":6},{"port":[59202,59202],"proto":6}],"action":"ALLOW","priority":100},{"consumer_filter_id":"5a167344497d4f3576da7854","provider_filter_id":"5a5bf0af497d4f55e5727f2a","consumer_filter_name":"Default","provider_filter_name":"scdf-esmallweb","l4_params":[{"port":[53,53],"proto":17},{"port":[80,80],"proto":6},{"port":[443,443],"proto":6}],"action":"ALLOW","priority":100},{"consumer_filter_id":"5a5bf0af497d4f55e5727f28","provider_filter_id":"5a43193c497d4f44784e1ee6","consumer_filter_name":"10.253.42.*","provider_filter_name":"Default:Public","l4_params":[{"port":[443,443],"proto":6}],"action":"ALLOW","priority":100},{"consumer_filter_id":"5a5bf0af497d4f55e5727f26","provider_filter_id":"5a167344497d4f3576da7854","consumer_filter_name":"scdf-es*","provider_filter_name":"Default","l4_params":[{"port":[53,53],"proto":17},{"port":[123,123],"proto":17},{"port":[25,25],"proto":6},{"port":[80,80],"proto":6},{"port":[3000,3000],"proto":6},{"port":[8100,8100],"proto":6},{"port":[40000,40000],"proto":6},{"port":[60000,60000],"proto":6}],"action":"ALLOW","priority":100},{"consumer_filter_id":"5a5bf0af497d4f55e5727f24","provider_filter_id":"5a41dfc9755f025cafc8d396","consumer_filter_name":"csh-iux-biwas","provider_filter_name":"Default:DataCenter:ServerFarm","l4_params":[{"port":[40536,40536],"proto":6},{"port":[123,123],"proto":17},{"port":[657,657],"proto":17}],"action":"ALLOW","priority":100},{"consumer_filter_id":"5a41dfc9755f025cafc8d396","provider_filter_id":"5a5bf0af497d4f55e5727f25","consumer_filter_name":"Default:DataCenter:ServerFarm","provider_filter_name":"scsdf-iweb","l4_params":[{"port":[30041,30041],"proto":6},{"port":[31003,31003],"proto":6}],"action":"ALLOW","priority":100},{"consumer_filter_id":"5a5bf0af497d4f55e5727f2a","provider_filter_id":"5a39c724497d4f4eb64e1e6b","consumer_filter_name":"scdf-esmallweb","provider_filter_name":"Default:DataCenter:nat","l4_params":[{"port":[123,123],"proto":17},{"port":[21,21],"proto":6},{"port":[1556,1556],"proto":6},{"port":[4700,36400],"proto":6},{"port":[37951,37951],"proto":6},{"port":[38820,60000],"proto":6}],"action":"ALLOW","priority":100},{"consumer_filter_id":"5a43193c497d4f44784e1ee6","provider_filter_id":"5a5bf0af497d4f55e5727f2b","consumer_filter_name":"Default:Public","provider_filter_name":"scdf-esmallweb","l4_params":[{"port":[80,80],"proto":6},{"port":[443,443],"proto":6},{"port":[1556,1556],"proto":6}],"action":"ALLOW","priority":100},{"consumer_filter_id":"5a5bf0af497d4f55e5727f23","provider_filter_id":"5a41dfc9755f025cafc8d396","consumer_filter_name":"cluster","provider_filter_name":"Default:DataCenter:ServerFarm","l4_params":[{"port":[110,110],"proto":6},{"port":[1521,1521],"proto":6},{"port":[41128,41128],"proto":6},{"port":[123,123],"proto":17}],"action":"ALLOW","priority":100},{"consumer_filter_id":"5a167344497d4f3576da7854","provider_filter_id":"5a5bf0af497d4f55e5727f27","consumer_filter_name":"Default","provider_filter_name":"dr-sdfmallexdb_dr-sdfexdb","l4_params":[{"port":[21113,21113],"proto":6}],"action":"ALLOW","priority":100},{"consumer_filter_id":"5a5bf0af497d4f55e5727f28","provider_filter_id":"5a5bf0af497d4f55e5727f2c","consumer_filter_name":"10.253.42.*","provider_filter_name":"10.253.42.102","l4_params":[{"port":[0,0],"proto":17},{"port":[2404,2404],"proto":17}],"action":"ALLOW","priority":100},{"consumer_filter_id":"5a5bf0af497d4f55e5727f20","provider_filter_id":"5a167344497d4f3576da7854","consumer_filter_name":"sdfexdb","provider_filter_name":"Default","l4_params":[{"port":[21,21],"proto":6},{"port":[1212,1212],"proto":6},{"port":[1556,1556],"proto":6},{"port":[3081,3081],"proto":6},{"port":[12701,12701],"proto":6},{"port":[19228,19228],"proto":6},{"port":[21080,21080],"proto":6},{"port":[31844,31844],"proto":6},{"port":[36214,36214],"proto":6},{"port":[38576,38576],"proto":6},{"port":[40929,40929],"proto":6},{"port":[41453,41453],"proto":6},{"port":[44855,44855],"proto":6},{"port":[44916,44916],"proto":6},{"port":[47492,47492],"proto":6},{"port":[53095,53095],"proto":6},{"port":[53640,53640],"proto":6},{"port":[56973,56973],"proto":6},{"port":[58123,58123],"proto":6},{"port":[58298,58298],"proto":6},{"port":[61574,61574],"proto":6},{"port":[53,53],"proto":17},{"port":[123,123],"proto":17},{"port":[5353,5353],"proto":17}],"action":"ALLOW","priority":100},{"consumer_filter_id":"5a5bf0af497d4f55e5727f21","provider_filter_id":"5a167344497d4f3576da7854","consumer_filter_name":"csh-iedi_scsdf-iedi-inf","provider_filter_name":"Default","l4_params":[{"port":[53,53],"proto":17},{"port":[123,123],"proto":17},{"port":[137,138],"proto":17},{"port":[5355,5355],"proto":17},{"port":[51202,51202],"proto":17},{"port":[55464,55464],"proto":17},{"port":[80,80],"proto":6},{"port":[443,443],"proto":6},{"port":[1556,1556],"proto":6},{"port":[3140,3141],"proto":6},{"port":[9979,9979],"proto":6},{"port":[38120,38120],"proto":6},{"port":[40328,40328],"proto":6},{"port":[53971,53971],"proto":6},{"port":[54127,54127],"proto":6},{"port":[61294,61294],"proto":6}],"action":"ALLOW","priority":100},{"consumer_filter_id":"5a39c826755f0270c4c8d278","provider_filter_id":"5a5bf0af497d4f55e5727f24","consumer_filter_name":"Default:DataCenter:dfs:dev","provider_filter_name":"csh-iux-biwas","l4_params":[{"port":[8009,8009],"proto":6}],"action":"ALLOW","priority":100},{"consumer_filter_id":"5a5bf0af497d4f55e5727f2c","provider_filter_id":"5a167344497d4f3576da7854","consumer_filter_name":"10.253.42.102","provider_filter_name":"Default","l4_params":[{"port":[21,21],"proto":6},{"port":[1556,1556],"proto":6},{"port":[5572,5572],"proto":6},{"port":[18710,18710],"proto":6},{"port":[39507,39507],"proto":6},{"port":[50448,50448],"proto":6},{"port":[57273,57273],"proto":6},{"port":[123,123],"proto":17},{"port":[5353,5353],"proto":17}],"action":"ALLOW","priority":100},{"consumer_filter_id":"5a167344497d4f3576da7854","provider_filter_id":"5a5bf0af497d4f55e5727f2c","consumer_filter_name":"Default","provider_filter_name":"10.253.42.102","l4_params":[{"port":[22,22],"proto":6},{"port":[1521,1521],"proto":6},{"port":[1556,1556],"proto":6},{"port":[10484,10484],"proto":6},{"port":[21003,21003],"proto":6},{"port":[21113,21113],"proto":6},{"port":[27377,27377],"proto":6}],"action":"ALLOW","priority":100},{"consumer_filter_id":"5a39c826755f0270c4c8d278","provider_filter_id":"5a5bf0af497d4f55e5727f20","consumer_filter_name":"Default:DataCenter:dfs:dev","provider_filter_name":"sdfexdb","l4_params":[{"port":[22,22],"proto":6}],"action":"ALLOW","priority":100},{"consumer_filter_id":"5a39c724497d4f4eb64e1e6b","provider_filter_id":"5a5bf0af497d4f55e5727f2b","consumer_filter_name":"Default:DataCenter:nat","provider_filter_name":"scdf-esmallweb","l4_params":[{"port":[22,22],"proto":6},{"port":[80,80],"proto":6},{"port":[443,443],"proto":6},{"port":[1556,1556],"proto":6},{"port":[5002,5003],"proto":6},{"port":[9900,9903],"proto":6},{"port":[21003,21003],"proto":6},{"port":[21113,21113],"proto":6},{"port":[30041,30041],"proto":6},{"port":[31003,31003],"proto":6}],"action":"ALLOW","priority":100},{"consumer_filter_id":"5a39c826755f0270c4c8d278","provider_filter_id":"5a5bf0af497d4f55e5727f2c","consumer_filter_name":"Default:DataCenter:dfs:dev","provider_filter_name":"10.253.42.102","l4_params":[{"port":[1521,1521],"proto":6},{"port":[5080,5080],"proto":6}],"action":"ALLOW","priority":100},{"consumer_filter_id":"5a5bf0af497d4f55e5727f2b","provider_filter_id":"5a41dfc9755f025cafc8d396","consumer_filter_name":"scdf-esmallweb","provider_filter_name":"Default:DataCenter:ServerFarm","l4_params":[{"port":[443,443],"proto":6},{"port":[5640,5640],"proto":6}],"action":"ALLOW","priority":100},{"consumer_filter_id":"5a5bf0af497d4f55e5727f2a","provider_filter_id":"5a5bf0af497d4f55e5727f26","consumer_filter_name":"scdf-esmallweb","provider_filter_name":"scdf-es*","l4_params":[{"port":[2314,2314],"proto":6}],"action":"ALLOW","priority":100},{"consumer_filter_id":"5a41dfc9755f025cafc8d396","provider_filter_id":"5a5bf0af497d4f55e5727f23","consumer_filter_name":"Default:DataCenter:ServerFarm","provider_filter_name":"cluster","l4_params":[{"port":[443,443],"proto":6},{"port":[1556,1556],"proto":6},{"port":[31003,31003],"proto":6}],"action":"ALLOW","priority":100},{"consumer_filter_id":"5a5bf0af497d4f55e5727f24","provider_filter_id":"5a41e741497d4f22824e200b","consumer_filter_name":"csh-iux-biwas","provider_filter_name":"Default:DataCenter:SDN","l4_params":[{"port":[1521,1521],"proto":6}],"action":"ALLOW","priority":100},{"consumer_filter_id":"5a5bf0af497d4f55e5727f26","provider_filter_id":"5a5bf0af497d4f55e5727f28","consumer_filter_name":"scdf-es*","provider_filter_name":"10.253.42.*","l4_params":[{"port":[32768,61500],"proto":6}],"action":"ALLOW","priority":100}],"catch_all_action":"DENY","clusters":[{"name":"10.253.42.*","id":"5a5bf0af497d4f55e5727f28","nodes":[{"ip":"10.253.42.161","name":"10.253.42.161"},{"ip":"10.253.42.162","name":"10.253.42.162"},{"ip":"10.253.42.163","name":"10.253.42.163"},{"ip":"10.253.42.164","name":"10.253.42.164"},{"ip":"10.253.42.174","name":"10.253.42.174"},{"ip":"10.253.42.175","name":"10.253.42.175"},{"ip":"10.253.42.91","name":"10.253.42.91"},{"ip":"10.253.42.92","name":"10.253.42.92"}],"external":false,"cluster_queries":[]},{"name":"10.253.42.101","id":"5a5bf0af497d4f55e5727f29","nodes":[{"ip":"10.253.42.101","name":"10.253.42.101"}],"external":false,"cluster_queries":[]},{"name":"10.253.42.102","id":"5a5bf0af497d4f55e5727f2c","nodes":[{"ip":"10.253.42.102","name":"10.253.42.102"}],"external":false,"cluster_queries":[]},{"name":"cluster","id":"5a5bf0af497d4f55e5727f23","nodes":[{"ip":"10.253.42.190","name":"10.253.42.190"},{"ip":"202.3.30.150","name":"202.3.30.150"}],"external":false,"cluster_queries":[]},{"name":"csh-iedi_scsdf-iedi-inf","id":"5a5bf0af497d4f55e5727f21","nodes":[{"ip":"10.102.96.25","name":"10.102.96.25"},{"ip":"10.253.41.212","name":"10.253.41.212"}],"external":false,"cluster_queries":[]},{"name":"csh-iux-biwas","id":"5a5bf0af497d4f55e5727f24","nodes":[{"ip":"10.102.96.27","name":"10.102.96.27"},{"ip":"10.102.96.28","name":"10.102.96.28"}],"external":false,"cluster_queries":[]},{"name":"csh-iux-db","id":"5a5bf0af497d4f55e5727f1d","nodes":[{"ip":"10.253.41.160","name":"10.253.41.160"}],"external":false,"cluster_queries":[]},{"name":"dr-sdfmallexdb_dr-sdfexdb","id":"5a5bf0af497d4f55e5727f27","nodes":[{"ip":"10.103.96.31","name":"10.103.96.31"},{"ip":"10.103.96.32","name":"10.103.96.32"},{"ip":"10.253.42.179","name":"10.253.42.179"},{"ip":"10.253.42.180","name":"10.253.42.180"}],"external":false,"cluster_queries":[]},{"name":"scdf-es*","id":"5a5bf0af497d4f55e5727f26","nodes":[{"ip":"202.3.30.120","name":"scdf-esapm"},{"ip":"202.3.30.111","name":"scdf-esems1"},{"ip":"202.3.30.114","name":"scdf-esimg1"},{"ip":"202.3.30.115","name":"scdf-esimg2"},{"ip":"202.3.30.117","name":"scdf-essearch1"},{"ip":"202.3.30.118","name":"scdf-essearch2"},{"ip":"202.3.30.112","name":"scdf-essms"}],"external":false,"cluster_queries":[]},{"name":"scdf-esmallweb","id":"5a5bf0af497d4f55e5727f2a","nodes":[{"ip":"202.3.30.179","name":"scdf-esmallweb5"},{"ip":"202.3.30.180","name":"scdf-esmallweb6"}],"external":false,"cluster_queries":[]},{"name":"scdf-esmallweb","id":"5a5bf0af497d4f55e5727f2b","nodes":[{"ip":"202.3.30.141","name":"scdf-esmallweb1"},{"ip":"202.3.30.142","name":"scdf-esmallweb2"},{"ip":"202.3.30.143","name":"scdf-esmallweb3"},{"ip":"202.3.30.144","name":"scdf-esmallweb4"}],"external":false,"cluster_queries":[]},{"name":"scsdf-iwas","id":"5a5bf0af497d4f55e5727f22","nodes":[{"ip":"10.102.96.21","name":"10.102.96.21"},{"ip":"10.102.96.22","name":"10.102.96.22"},{"ip":"10.102.96.23","name":"10.102.96.23"}],"external":false,"cluster_queries":[]},{"name":"scsdf-iweb","id":"5a5bf0af497d4f55e5727f25","nodes":[{"ip":"10.101.96.21","name":"10.101.96.21"},{"ip":"10.101.96.22","name":"10.101.96.22"}],"external":false,"cluster_queries":[]},{"name":"sdfexdb","id":"5a5bf0af497d4f55e5727f20","nodes":[{"ip":"10.102.96.24","name":"10.102.96.24"},{"ip":"10.103.96.21","name":"10.103.96.21"},{"ip":"10.103.96.22","name":"10.103.96.22"}],"external":false,"cluster_queries":[]}],"inventory_filters":[{"id":"5a167344497d4f3576da7854","name":"Default","query":{"type":"eq","field":"vrf_id","value":1}},{"id":"5a39c6d0497d4f50484e1e6b","name":"Default:DataCenter","query":{"type":"and","filters":[{"field":"vrf_id","type":"eq","value":1},{"type":"or","filters":[{"field":"ip","type":"subnet","value":"10.16.0.0/12"},{"field":"ip","type":"subnet","value":"10.96.0.0/12"},{"field":"ip","type":"subnet","value":"10.100.0.0/16"},{"field":"ip","type":"subnet","value":"10.253.0.0/16"},{"field":"ip","type":"subnet","value":"10.21.21.0/24"},{"field":"ip","type":"subnet","value":"10.21.30.0/24"},{"field":"ip","type":"subnet","value":"202.3.30.0/24"},{"field":"ip","type":"subnet","value":"202.3.28.0/24"},{"field":"ip","type":"subnet","value":"60.196.0.0/24"}]}]},"parent_app_scope":{"id":"5a167344497d4f3576da7854","name":"Default"}},{"id":"5a39c826755f0270c4c8d278","name":"Default:DataCenter:dfs:dev","query":{"type":"and","filters":[{"field":"vrf_id","type":"eq","value":1},{"type":"or","filters":[{"field":"ip","type":"subnet","value":"10.16.0.0/12"},{"field":"ip","type":"subnet","value":"10.96.0.0/12"},{"field":"ip","type":"subnet","value":"10.100.0.0/16"},{"field":"ip","type":"subnet","value":"10.253.0.0/16"},{"field":"ip","type":"subnet","value":"10.21.21.0/24"},{"field":"ip","type":"subnet","value":"10.21.30.0/24"},{"field":"ip","type":"subnet","value":"202.3.30.0/24"},{"field":"ip","type":"subnet","value":"202.3.28.0/24"},{"field":"ip","type":"subnet","value":"60.196.0.0/24"}]},{"field":"user_COMPANY","type":"contains","value":"dfs"},{"type":"not","filter":{"field":"user_LIFECYCLE","type":"contains","value":"operation"}}]},"parent_app_scope":{"id":"5a39c78a755f027269c8d278","name":"Default:DataCenter:dfs"}},{"id":"5a39c80d755f0241ffc8d280","name":"Default:DataCenter:dfs:prod","query":{"type":"and","filters":[{"field":"vrf_id","type":"eq","value":1},{"type":"or","filters":[{"field":"ip","type":"subnet","value":"10.16.0.0/12"},{"field":"ip","type":"subnet","value":"10.96.0.0/12"},{"field":"ip","type":"subnet","value":"10.100.0.0/16"},{"field":"ip","type":"subnet","value":"10.253.0.0/16"},{"field":"ip","type":"subnet","value":"10.21.21.0/24"},{"field":"ip","type":"subnet","value":"10.21.30.0/24"},{"field":"ip","type":"subnet","value":"202.3.30.0/24"},{"field":"ip","type":"subnet","value":"202.3.28.0/24"},{"field":"ip","type":"subnet","value":"60.196.0.0/24"}]},{"field":"user_COMPANY","type":"contains","value":"dfs"},{"field":"user_LIFECYCLE","type":"contains","value":"operation"}]},"parent_app_scope":{"id":"5a39c78a755f027269c8d278","name":"Default:DataCenter:dfs"}},{"id":"5a39c724497d4f4eb64e1e6b","name":"Default:DataCenter:nat","query":{"type":"and","filters":[{"field":"vrf_id","type":"eq","value":1},{"type":"or","filters":[{"field":"ip","type":"subnet","value":"10.16.0.0/12"},{"field":"ip","type":"subnet","value":"10.96.0.0/12"},{"field":"ip","type":"subnet","value":"10.100.0.0/16"},{"field":"ip","type":"subnet","value":"10.253.0.0/16"},{"field":"ip","type":"subnet","value":"10.21.21.0/24"},{"field":"ip","type":"subnet","value":"10.21.30.0/24"},{"field":"ip","type":"subnet","value":"202.3.30.0/24"},{"field":"ip","type":"subnet","value":"202.3.28.0/24"},{"field":"ip","type":"subnet","value":"60.196.0.0/24"}]},{"type":"or","filters":[{"field":"ip","type":"subnet","value":"10.100.111.0/24"},{"field":"ip","type":"subnet","value":"10.100.112.0/24"},{"field":"ip","type":"subnet","value":"10.100.113.0/24"},{"field":"ip","type":"subnet","value":"10.100.114.0/24"},{"field":"ip","type":"subnet","value":"10.100.116.0/24"},{"field":"ip","type":"subnet","value":"10.100.117.0/24"}]}]},"parent_app_scope":{"id":"5a39c6d0497d4f50484e1e6b","name":"Default:DataCenter"}},{"id":"5a41e741497d4f22824e200b","name":"Default:DataCenter:SDN","query":{"type":"and","filters":[{"field":"vrf_id","type":"eq","value":1},{"type":"or","filters":[{"field":"ip","type":"subnet","value":"10.16.0.0/12"},{"field":"ip","type":"subnet","value":"10.96.0.0/12"},{"field":"ip","type":"subnet","value":"10.100.0.0/16"},{"field":"ip","type":"subnet","value":"10.253.0.0/16"},{"field":"ip","type":"subnet","value":"10.21.21.0/24"},{"field":"ip","type":"subnet","value":"10.21.30.0/24"},{"field":"ip","type":"subnet","value":"202.3.30.0/24"},{"field":"ip","type":"subnet","value":"202.3.28.0/24"},{"field":"ip","type":"subnet","value":"60.196.0.0/24"}]},{"type":"or","filters":[{"field":"ip","type":"subnet","value":"10.101.0.0/16"},{"field":"ip","type":"subnet","value":"10.102.0.0/16"},{"field":"ip","type":"subnet","value":"10.103.0.0/16"},{"field":"ip","type":"subnet","value":"10.104.0.0/16"},{"field":"ip","type":"subnet","value":"10.105.0.0/16"},{"field":"ip","type":"subnet","value":"10.106.0.0/16"},{"field":"ip","type":"subnet","value":"10.107.0.0/16"},{"field":"ip","type":"subnet","value":"10.108.0.0/16"},{"field":"ip","type":"subnet","value":"10.109.0.0/16"},{"field":"ip","type":"subnet","value":"10.110.0.0/16"},{"field":"ip","type":"subnet","value":"10.111.0.0/16"},{"field":"ip","type":"subnet","value":"10.112.0.0/16"},{"field":"ip","type":"subnet","value":"10.113.0.0/16"},{"field":"ip","type":"subnet","value":"10.114.0.0/16"},{"field":"ip","type":"subnet","value":"10.115.0.0/16"},{"field":"ip","type":"subnet","value":"10.116.0.0/16"},{"field":"ip","type":"subnet","value":"10.117.0.0/16"},{"field":"ip","type":"subnet","value":"10.118.0.0/16"},{"field":"ip","type":"subnet","value":"10.119.0.0/16"}]}]},"parent_app_scope":{"id":"5a39c6d0497d4f50484e1e6b","name":"Default:DataCenter"}},{"id":"5a41dfc9755f025cafc8d396","name":"Default:DataCenter:ServerFarm","query":{"type":"and","filters":[{"field":"vrf_id","type":"eq","value":1},{"type":"or","filters":[{"field":"ip","type":"subnet","value":"10.16.0.0/12"},{"field":"ip","type":"subnet","value":"10.96.0.0/12"},{"field":"ip","type":"subnet","value":"10.100.0.0/16"},{"field":"ip","type":"subnet","value":"10.253.0.0/16"},{"field":"ip","type":"subnet","value":"10.21.21.0/24"},{"field":"ip","type":"subnet","value":"10.21.30.0/24"},{"field":"ip","type":"subnet","value":"202.3.30.0/24"},{"field":"ip","type":"subnet","value":"202.3.28.0/24"},{"field":"ip","type":"subnet","value":"60.196.0.0/24"}]},{"type":"or","filters":[{"field":"ip","type":"subnet","value":"174.100.2.0/24"},{"field":"ip","type":"subnet","value":"174.100.20.0/24"},{"field":"ip","type":"subnet","value":"174.100.21.0/24"},{"field":"ip","type":"subnet","value":"174.100.22.0/24"},{"field":"ip","type":"subnet","value":"174.100.23.0/24"},{"field":"ip","type":"subnet","value":"174.100.24.0/24"},{"field":"ip","type":"subnet","value":"174.100.25.0/24"},{"field":"ip","type":"subnet","value":"174.100.26.0/24"},{"field":"ip","type":"subnet","value":"174.100.27.0/24"},{"field":"ip","type":"subnet","value":"174.100.28.0/24"},{"field":"ip","type":"subnet","value":"174.100.67.0/24"},{"field":"ip","type":"subnet","value":"10.253.0.0/16"}]}]},"parent_app_scope":{"id":"5a39c6d0497d4f50484e1e6b","name":"Default:DataCenter"}},{"id":"5a43193c497d4f44784e1ee6","name":"Default:Public","query":{"type":"and","filters":[{"field":"vrf_id","type":"eq","value":1},{"type":"or","filters":[{"field":"ip","type":"subnet","value":"14.36.32.0/24"},{"field":"ip","type":"subnet","value":"210.92.198.0/24"},{"field":"ip","type":"subnet","value":"112.171.0.0/20"},{"field":"ip","type":"subnet","value":"112.171.117.0/24"},{"field":"ip","type":"subnet","value":"121.140.97.0/24"},{"field":"ip","type":"subnet","value":"121.140.152.0/24"},{"field":"ip","type":"subnet","value":"121.170.176.0/22"},{"field":"ip","type":"subnet","value":"202.3.16.0/20"},{"field":"ip","type":"subnet","value":"202.8.106.0/24"},{"field":"ip","type":"subnet","value":"202.8.160.0/19"},{"field":"ip","type":"subnet","value":"210.92.221.0/24"}]}]},"parent_app_scope":{"id":"5a167344497d4f3576da7854","name":"Default"}}],"vrf":{"id":1,"name":"Default","tenant_id":0,"tenant_name":"Default"}}